framework/__init__.py
framework/allure_report.py
framework/base_class.py
framework/conftest.py
framework/exit_code.py
framework/extract.py
framework/global_attribute.py
framework/http_client.py
framework/render_data.py
framework/startapp.py
framework/validate.py
framework/db/__init__.py
framework/db/mysql_db.py
framework/db/redis_db.py
framework/utils/__init__.py
framework/utils/common.py
framework/utils/encrypt.py
framework/utils/log_util.py
framework/utils/teams_util.py
framework/utils/yaml_util.py
pytest_api_framework-0.4.0.dist-info/METADATA
pytest_api_framework-0.4.0.dist-info/WHEEL
pytest_api_framework-0.4.0.dist-info/top_level.txt
pytest_api_framework-0.4.0.dist-info/RECORD
