Metadata-Version: 2.4
Name: pytest-api-framework
Version: 0.4.0
Summary: pytest framework
Author: wangjinliang
Author-email: wangjinliang219@gmail.com
Requires-Dist: PyMySQL==1.1.0
Requires-Dist: redis==3.5.3
Requires-Dist: DBUtils==3.1.0
Requires-Dist: pyotp==2.9.0
Requires-Dist: cn2an==0.5.19
Requires-Dist: python-dotenv==1.0.1
Requires-Dist: pycryptodome==3.21.0
Requires-Dist: requests==2.25.1
Requires-Dist: PyYAML==6.0.2
Requires-Dist: python-box==7.2.0
Requires-Dist: allure-pytest==2.13.1
Requires-Dist: dill==0.4.0
Requires-Dist: pytest==7.2.2
Requires-Dist: jsonpath==0.82
Requires-Dist: requests-toolbelt==1.0.0
Requires-Dist: Faker==18.3.2
Requires-Dist: retry==0.9.2
Dynamic: author
Dynamic: author-email
Dynamic: requires-dist
Dynamic: summary
